YoudaoTranslateClass
