Metadata-Version: 2.1
Name: YoudaoTranslate
Version: 0.0.2
Summary: PyPI YoudaoTranslate
Home-page: https://github.com/laughterGod
Author: hanziguo
Author-email: hanziguo@foxmail.com
License: UNKNOWN
Platform: UNKNOWN
Classifier: Programming Language :: Python :: 3
Classifier: License :: OSI Approved :: MIT License
Classifier: Operating System :: OS Independent
